tests/__init__.py
tests/test_exceptions.py
tests/test_fields.py
tests/test_validators.py
tests/utils.py
tests/ext/__init__.py
tests/ext/django/__init__.py
tests/ext/django/models.py
tests/ext/django/settings.py
tests/ext/django/test_fields.py
valedictory/__init__.py
valedictory/base.py
valedictory/exceptions.py
valedictory/fields.py
valedictory/validator.py
valedictory/version.py
valedictory/ext/__init__.py
valedictory/ext/django.py
valedictory-0.8.0.dist-info/METADATA
valedictory-0.8.0.dist-info/RECORD
valedictory-0.8.0.dist-info/WHEEL
valedictory-0.8.0.dist-info/top_level.txt
