Metadata-Version: 2.1
Name: valedictory
Version: 0.8.0
Summary: Validate dicts against a schema
Home-page: https://github.com/timheap/valedictory/
Author: Tim Heap
Author-email: tim@timheap.me
License: BSD License
Project-URL: Bug Tracker, https://github.com/timheap/valedictory/issues
Project-URL: Documentation, https://valedictory.readthedocs.io
Project-URL: Source Code, https://github.com/timheap/valedictory
Platform: UNKNOWN
Classifier: Environment :: Web Environment
Classifier: Intended Audience :: Developers
Classifier: Operating System :: OS Independent
Classifier: Programming Language :: Python
Classifier: Programming Language :: Python :: 3
Classifier: Programming Language :: Python :: 3.4
Classifier: Programming Language :: Python :: 3.5
Classifier: Programming Language :: Python :: 3.6
Classifier: Programming Language :: Python :: 3.7
Classifier: Framework :: Django
Classifier: License :: OSI Approved :: BSD License
Requires-Dist: aniso8601 (~=3.0.0)
